harreither_brain_client/__init__.py
harreither_brain_client/authenticate.py
harreither_brain_client/cli.py
harreither_brain_client/connection.py
harreither_brain_client/data.py
harreither_brain_client/entries.py
harreither_brain_client/establish_connection.py
harreither_brain_client/message.py
harreither_brain_client/receive.py
harreither_brain_client/traverse_screens.py
harreither_brain_client/type_int.py
harreither_brain_client-0.3.0.dist-info/licenses/LICENSE
harreither_brain_client-0.3.0.dist-info/METADATA
harreither_brain_client-0.3.0.dist-info/WHEEL
harreither_brain_client-0.3.0.dist-info/entry_points.txt
harreither_brain_client-0.3.0.dist-info/top_level.txt
harreither_brain_client-0.3.0.dist-info/RECORD
