Metadata-Version: 2.4
Name: harreither-brain-client
Version: 0.3.0
Summary: Unofficial client library and CLI for Harreither Brain devices
Author: Andraz Tori
License: MIT License
Project-URL: Homepage, https://github.com/andraztori/harreither-brain-client
Project-URL: Repository, https://github.com/andraztori/harreither-brain-client
Keywords: harreither,client
Classifier: Development Status :: 3 - Alpha
Classifier: Intended Audience :: Developers
Classifier: License :: OSI Approved :: MIT License
Classifier: Programming Language :: Python
Classifier: Programming Language :: Python :: 3
Classifier: Programming Language :: Python :: 3.10
Classifier: Programming Language :: Python :: 3.11
Classifier: Programming Language :: Python :: 3.12
Classifier: Programming Language :: Python :: 3.13
Classifier: Topic :: Internet :: WWW/HTTP
Classifier: Topic :: Software Development :: Libraries
Requires-Python: >=3.10
License-File: LICENSE
Requires-Dist: websockets>=12.0
Requires-Dist: cryptography>=41.0
Dynamic: license-file
